amr_coref/coref/__init__.py
amr_coref/coref/amr_coref_model.py
amr_coref/coref/build_coref_tdata.py
amr_coref/coref/build_embeddings.py
amr_coref/coref/clustering.py
amr_coref/coref/coref_data_loader.py
amr_coref/coref/coref_dataset.py
amr_coref/coref/coref_featurizer.py
amr_coref/coref/coref_mention_data.py
amr_coref/coref/inference.py
amr_coref/coref/multi_sentence_amr.py
amr_coref/coref/penman_multisentence.py
amr_coref/coref/penman_serializer.py
amr_coref/coref/tester.py
amr_coref/coref/trainer.py
amr_coref/coref/vocab_embeddings.py
amr_coref/coref/word_vectors.py
amr_coref/evaluate/__init__.py
amr_coref/evaluate/pr_scorer.py
amr_coref/evaluate/scorch.py
amr_coref/evaluate/scorch_scores.py
amr_coref/utils/__init__.py
amr_coref/utils/config.py
amr_coref/utils/data_utils.py
amr_coref/utils/log_splitter.py
amr_coref/utils/logging.py
zensols.amr_coref-0.0.2.dist-info/LICENSE.txt
zensols.amr_coref-0.0.2.dist-info/METADATA
zensols.amr_coref-0.0.2.dist-info/WHEEL
zensols.amr_coref-0.0.2.dist-info/top_level.txt
zensols.amr_coref-0.0.2.dist-info/RECORD
