Metadata-Version: 2.1
Name: zensols.amr-coref
Version: 0.0.2
Summary: A python library / model for creating co-references between AMR graph nodes.
Home-page: https://github.com/plandes/amr_coref
Download-URL: https://github.com/plandes/amr_coref/releases/download/v0.0.2/zensols.amr_coref-0.0.2-py3-none-any.whl
Author: Paul Landes
Author-email: landes@mailc.net
Keywords: tooling
Classifier: Programming Language :: Python :: 3
Classifier: License :: OSI Approved :: MIT License
Classifier: Operating System :: OS Independent
License-File: LICENSE.txt
Requires-Dist: numpy
Requires-Dist: penman
Requires-Dist: scipy
Requires-Dist: torch
Requires-Dist: tqdm
